meteofrance_publicapi/__init__.py
meteofrance_publicapi/const.py
meteofrance_publicapi/core.py
meteofrance_publicapi/errors.py
meteofrance_publicapi/forecast.py
meteofrance_publicapi/observations.py
meteofrance_publicapi/raster.py
meteofrance_publicapi/tests/__inti__.py
meteofrance_publicapi/tests/test_import.py
meteofrance_publicapi-0.1.5.dist-info/LICENSE
meteofrance_publicapi-0.1.5.dist-info/METADATA
meteofrance_publicapi-0.1.5.dist-info/WHEEL
meteofrance_publicapi-0.1.5.dist-info/top_level.txt
meteofrance_publicapi-0.1.5.dist-info/RECORD
