Metadata-Version: 2.1
Name: meteofrance-publicapi
Version: 0.1.5
Summary: A wrapper of the portail-api.meteofrance.fr datasets
Author: Antoine Tavant
License: 
Project-URL: Homepage, https://github.com/antoinetavant/meteofranceapi
Project-URL: Bug Tracker, https://github.com/antoinetavant/meteofranceapi/issues
Classifier: Programming Language :: Python :: 3 :: Only
Classifier: Programming Language :: Python :: 3.9
Classifier: Programming Language :: Python :: 3.10
Classifier: Programming Language :: Python :: 3.11
Classifier: Programming Language :: Python :: 3.12
Classifier: License :: OSI Approved :: GNU General Public License v3 (GPLv3)
Classifier: Operating System :: OS Independent
Classifier: Intended Audience :: Developers
Classifier: Development Status :: 2 - Pre-Alpha
Classifier: Topic :: Scientific/Engineering :: Atmospheric Science
Requires-Python: >=3.9
License-File: LICENSE
Requires-Dist: pandas
Requires-Dist: numpy
Requires-Dist: scipy
Requires-Dist: deprecation
Requires-Dist: requests
Requires-Dist: xmltodict
Requires-Dist: rasterio
Requires-Dist: cartopy
Requires-Dist: matplotlib
Provides-Extra: doc
Requires-Dist: sphinx; extra == "doc"
Requires-Dist: pydata-sphinx-theme; extra == "doc"
Requires-Dist: sphinx_design; extra == "doc"
Requires-Dist: nbsphinx; extra == "doc"
Provides-Extra: test
Requires-Dist: pytest; extra == "test"
Requires-Dist: pytest-cov; extra == "test"
Requires-Dist: python-dotenv; extra == "test"
Provides-Extra: all
Requires-Dist: meteofrance_publicapi[doc,test]; extra == "all"
